Metadata-Version: 2.1
Name: compare-concordance
Version: 0.0.2
Summary: Statistical inference about right-censored c-indices
Home-page: https://github.com/wjn0/compare_concordance
Author: Walter Nelson
Author-email: Walter Nelson <walterj.nelson@mail.utoronto.ca>
License:                     GNU GENERAL PUBLIC LICENSE
Project-URL: Homepage, https://github.com/wjn0/compare_concordance
Project-URL: Bug Tracker, https://github.com/wjn0/compare_concordance/issues
Classifier: Programming Language :: Python :: 3
Classifier: License :: OSI Approved :: MIT License
Classifier: Operating System :: OS Independent
Requires-Python: >=3.6
License-File: LICENSE
